pyallied/__init__.py
pyallied/api_crud/__init__.py
pyallied/api_crud/crud.py
pyallied/mobile/AndroidPoweOptions.py
pyallied/mobile/ClipboardContentType.py
pyallied/mobile/CommandMethod.py
pyallied/mobile/ConnectionType.py
pyallied/mobile/__init__.py
pyallied/mobile/appiumby.py
pyallied/mobile/applicationstate.py
pyallied/mobile/gsm.py
pyallied/mobile/key_event_keyCodes.py
pyallied/mobile/logTypes.py
pyallied/mobile/mobAppium.py
pyallied/mobile/mobAppium_actions.py
pyallied/mobile/mobilecommand.py
pyallied/mobile/network.py
pyallied/mobile/pollWait.py
pyallied/mobile/session.py
pyallied/web/DropDown.py
pyallied/web/ErrorCodes.py
pyallied/web/__init__.py
pyallied/web/alerts.py
pyallied/web/browser.py
pyallied/web/constants_WebDriver_commands.py
pyallied/web/dragAndDrop.py
pyallied/web/dragDrop.js
pyallied/web/file_detector.py
pyallied/web/firefox.py
pyallied/web/firefox_context.py
pyallied/web/keys.py
pyallied/web/log_type.py
pyallied/web/other_miscellaneous.py
pyallied/web/print_page_options.py
pyallied/web/test_path.py
pyallied/web/webElement.py
pyallied/web/webElement_v2.py
pyallied/web/webWaits.py
pyallied/web/wheel_input.py
pyallied/web/windowAndFrame.py
pyallied-1.0.21.dist-info/LICENSE
pyallied-1.0.21.dist-info/METADATA
pyallied-1.0.21.dist-info/WHEEL
pyallied-1.0.21.dist-info/top_level.txt
pyallied-1.0.21.dist-info/RECORD
