Metadata-Version: 2.1
Name: pyallied
Version: 1.0.21
Summary: pyallied - a wrapper based on selenium python
Home-page: https://github.com/srinivasaraojyothi/seleniumpythonactionbot.git
Author: srinivasaraojyothi@gmail.com
Author-email: srinivasaraojyothi@gmail.com
License: UNKNOWN
Project-URL: Bug Tracker, https://github.com/srinivasaraojyothi/seleniumpythonactionbot/issues
Platform: UNKNOWN
Classifier: Programming Language :: Python :: 3
Classifier: License :: OSI Approved :: MIT License
Classifier: Operating System :: OS Independent
Requires-Python: >=3.9
License-File: LICENSE
